pyfabrik/__init__.py
pyfabrik/client.py
pyfabrik/data.py
pyfabrik/models.py
oafabrik-0.9.0.dist-info/METADATA
oafabrik-0.9.0.dist-info/WHEEL
oafabrik-0.9.0.dist-info/top_level.txt
oafabrik-0.9.0.dist-info/RECORD
