Metadata-Version: 2.1
Name: oafabrik
Version: 0.9.0
Summary: A Python SDK for Fabrik
Home-page: https://github.com/openaristos/pyfabrik
Author: Aristos Data, LLC.
Author-email: hello@openaristos.io
License: AGPLv3
Keywords: openaristos,fabrik
Platform: UNKNOWN
Classifier: Development Status :: 4 - Beta
Classifier: License :: OSI Approved :: GNU Affero General Public License v3 or later (AGPLv3+)
Classifier: Topic :: Scientific/Engineering :: Information Analysis
Classifier: Topic :: Scientific/Engineering :: Artificial Intelligence
Classifier: Intended Audience :: Financial and Insurance Industry
Classifier: Intended Audience :: Developers
Classifier: Intended Audience :: Healthcare Industry
Classifier: Intended Audience :: Information Technology
Classifier: Intended Audience :: Science/Research
Classifier: Intended Audience :: Telecommunications Industry
Classifier: Programming Language :: Python
Classifier: Programming Language :: Python :: 3
Classifier: Programming Language :: Python :: 3.4
Classifier: Programming Language :: Python :: 3.5
Classifier: Programming Language :: Python :: 3.6
Classifier: Programming Language :: Python :: 3.7
Requires-Dist: pydantic
Requires-Dist: s3fs
Requires-Dist: pandas
Requires-Dist: requests
Requires-Dist: pyarrow
